{
  "type": "nucleoid_extras:styled/advanced_menu",
  "name": {
    "translate": "nucleoid.navigator.category.casual"
  },
  "icon": "minecraft:azalea_leaves",
  "entries": [
    {
      "type": "plasmid:portal",
      "portal": "build_rush:root"
    },
    {
      "type": "plasmid:portal",
      "portal": "nucleoid:build_battle"
    },
    {
      "type": "plasmid:portal",
      "portal": "nucleoid:infinite_parkour"
    },
    {
      "type": "plasmid:portal",
      "portal": "nucleoid:parkour_race"
    },
    {
      "type": "plasmid:portal",
      "portal": "nucleoid:parkour_run"
    },
    {
      "type": "plasmid:portal",
      "portal": "nucleoid:item_hunt"
    },
    {
      "type": "plasmid:portal",
      "portal": "nucleoid:murder_mystery"
    },
    {
      "type": "plasmid:portal",
      "portal": "nucleoid:quakecraft"
    }
  ]
}
